dmf/__init__.py
dmf/dmf.py
dmf/fbenm.py
dmf/interpolate.py
dmf/mpi_backend.py
pydmf-1.1.0.dist-info/licenses/LICENSE
pydmf-1.1.0.dist-info/METADATA
pydmf-1.1.0.dist-info/WHEEL
pydmf-1.1.0.dist-info/top_level.txt
pydmf-1.1.0.dist-info/RECORD
