Metadata-Version: 2.4
Name: pydmf
Version: 1.1.0
Summary: A Python package implementing the direct MaxFlux method and flat-bottom elastic network model for reaction path/transition state optimization.
Author-email: Shin-ichi Koda <koda@ims.ac.jp>
License: MIT License
Project-URL: Homepage, https://github.com/shin1koda/dmf
Project-URL: Source, https://github.com/shin1koda/dmf
Project-URL: Issues, https://github.com/shin1koda/dmf/issues
Keywords: reaction path,transition state,DFT,MaxFlux,elastic network model,chemistry,optimization
Classifier: Programming Language :: Python :: 3
Classifier: License :: OSI Approved :: MIT License
Classifier: Operating System :: OS Independent
Classifier: Topic :: Scientific/Engineering :: Chemistry
Requires-Python: >=3.8
License-File: LICENSE
Requires-Dist: ase>=3.22
Provides-Extra: cyipopt
Requires-Dist: cyipopt>=1.4; extra == "cyipopt"
Provides-Extra: dev
Requires-Dist: pytest; extra == "dev"
Requires-Dist: build; extra == "dev"
Requires-Dist: twine; extra == "dev"
Provides-Extra: docs
Requires-Dist: sphinx; extra == "docs"
Requires-Dist: sphinx_rtd_theme; extra == "docs"
Requires-Dist: sphinx-autodoc-typehints; extra == "docs"
Requires-Dist: ghp-import; extra == "docs"
Dynamic: license-file
